elsewhere_db-0.1.dist-info/METADATA
elsewhere_db-0.1.dist-info/RECORD
elsewhere_db-0.1.dist-info/WHEEL
elsewhere_db-0.1.dist-info/top_level.txt
ew_db/__init__.py
ew_db/db.py
ew_db/models.py
