Metadata-Version: 2.1
Name: elsewhere-db
Version: 0.1
Summary: Model for ordering menu and users
Home-page: https://gitlab.com/piar301/auth0-login
Author: Billy Lapatas
Author-email: piar301@gmail.com
License: MIT
Platform: UNKNOWN
Requires-Dist: Flask
Requires-Dist: Flask-SQLAlchemy
Requires-Dist: PyMySQL
